accarbon_command/__init__.py
accarbon_command/accarbon.py
accarbon_command/atcoder.py
accarbon_command/carbon.py
accarbon_command/env.py
accarbon_command/main.py
accarbon_command/twitter.py
accarbon-0.0.1.dist-info/LICENSE
accarbon-0.0.1.dist-info/METADATA
accarbon-0.0.1.dist-info/WHEEL
accarbon-0.0.1.dist-info/entry_points.txt
accarbon-0.0.1.dist-info/top_level.txt
accarbon-0.0.1.dist-info/RECORD
