Metadata-Version: 2.1
Name: accarbon
Version: 0.0.1
Summary: Tweet images of source code submitted to AtCoder.
Home-page: https://github.com/YunosukeY/ac-carbon-command
Author: kimitsu
Author-email: yunosuke@ueda.info.waseda.ac.jp
License: MIT
Keywords: atcoder carbon
Platform: UNKNOWN
Requires-Dist: beautifulsoup4
Requires-Dist: requests
Requires-Dist: requests-oauthlib
Requires-Dist: urllib3
